{
  "main": {
    "id": "da9fa0f33c2a615f",
    "type": "split",
    "children": [
      {
        "id": "4d5ec56e57395c88",
        "type": "tabs",
        "children": [
          {
            "id": "ed1a9be185e2aaac",
            "type": "leaf",
            "state": {
              "type": "markdown",
              "state": {
                "file": "Courses/Probabilistic AI/Probabilistic AI Roadmap.md",
                "mode": "source",
                "source": true
              },
              "icon": "lucide-file",
              "title": "Probabilistic AI Roadmap"
            }
          },
          {
            "id": "2e8575f5ec7f1a52",
            "type": "leaf",
            "state": {
              "type": "markdown",
              "state": {
                "file": "Probability Theory/Gaussian Distribution.md",
                "mode": "source",
                "source": true
              },
              "icon": "lucide-file",
              "title": "Gaussian Distribution"
            }
          },
          {
            "id": "4b59114e98643804",
            "type": "leaf",
            "state": {
              "type": "markdown",
              "state": {
                "file": "ML Theory/Variational Inference.md",
                "mode": "source",
                "source": true
              },
              "icon": "lucide-file",
              "title": "Variational Inference"
            }
          },
          {
            "id": "b32d5576afc99c70",
            "type": "leaf",
            "state": {
              "type": "markdown",
              "state": {
                "file": "Markov Processes/Markov Chain.md",
                "mode": "source",
                "source": true
              },
              "icon": "lucide-file",
              "title": "Markov Chain"
            }
          }
        ],
        "currentTab": 3
      },
      {
        "id": "7cfba2b510f9f98d",
        "type": "tabs",
        "children": [
          {
            "id": "464ee18910056598",
            "type": "leaf",
            "state": {
              "type": "markdown",
              "state": {
                "file": "Courses/Probabilistic AI/Probabilistic AI Roadmap.md",
                "mode": "preview",
                "source": true
              },
              "icon": "lucide-file",
              "title": "Probabilistic AI Roadmap"
            }
          },
          {
            "id": "d966487b880df0b8",
            "type": "leaf",
            "state": {
              "type": "markdown",
              "state": {
                "file": "Markov Processes/Stationary Distribution.md",
                "mode": "preview",
                "source": true
              },
              "icon": "lucide-file",
              "title": "Stationary Distribution"
            }
          },
          {
            "id": "2c3234f60697ca6f",
            "type": "leaf",
            "state": {
              "type": "markdown",
              "state": {
                "file": "Probability Theory/Gaussian Distribution.md",
                "mode": "preview",
                "source": true
              },
              "icon": "lucide-file",
              "title": "Gaussian Distribution"
            }
          },
          {
            "id": "003ebaaeb905c12d",
            "type": "leaf",
            "state": {
              "type": "markdown",
              "state": {
                "file": "ML Theory/Variational Inference.md",
                "mode": "preview",
                "source": true
              },
              "icon": "lucide-file",
              "title": "Variational Inference"
            }
          },
          {
            "id": "7c23c74e8323a679",
            "type": "leaf",
            "state": {
              "type": "markdown",
              "state": {
                "file": "ML Theory/Laplace Approximation.md",
                "mode": "preview",
                "source": true
              },
              "icon": "lucide-file",
              "title": "Laplace Approximation"
            }
          },
          {
            "id": "bdc35b4800862871",
            "type": "leaf",
            "state": {
              "type": "markdown",
              "state": {
                "file": "Probability Theory/Independence.md",
                "mode": "preview",
                "source": true
              },
              "icon": "lucide-file",
              "title": "Independence"
            }
          },
          {
            "id": "4c1b7de538ea8384",
            "type": "leaf",
            "state": {
              "type": "markdown",
              "state": {
                "file": "Probability Theory/Expected Value.md",
                "mode": "preview",
                "source": true
              },
              "icon": "lucide-file",
              "title": "Expected Value"
            }
          },
          {
            "id": "1cf617a12385de51",
            "type": "leaf",
            "state": {
              "type": "markdown",
              "state": {
                "file": "Markov Processes/Markov Chain.md",
                "mode": "preview",
                "source": true
              },
              "icon": "lucide-file",
              "title": "Markov Chain"
            }
          },
          {
            "id": "70079afab2ce302c",
            "type": "leaf",
            "state": {
              "type": "markdown",
              "state": {
                "file": "Measure Theory/Diffeomorphism.md",
                "mode": "preview",
                "source": true
              },
              "icon": "lucide-file",
              "title": "Diffeomorphism"
            }
          }
        ],
        "currentTab": 7
      }
    ],
    "direction": "vertical"
  },
  "left": {
    "id": "74ebf3055b564f0b",
    "type": "split",
    "children": [
      {
        "id": "595ad8f59f37c1e1",
        "type": "tabs",
        "children": [
          {
            "id": "ee568ad677adda89",
            "type": "leaf",
            "state": {
              "type": "file-explorer",
              "state": {
                "sortOrder": "alphabetical"
              },
              "icon": "lucide-folder-closed",
              "title": "Files"
            }
          },
          {
            "id": "426a3c97ada45d5c",
            "type": "leaf",
            "state": {
              "type": "search",
              "state": {
                "query": "change of variable",
                "matchingCase": false,
                "explainSearch": false,
                "collapseAll": false,
                "extraContext": false,
                "sortOrder": "alphabetical"
              },
              "icon": "lucide-search",
              "title": "Search"
            }
          },
          {
            "id": "60801509214fc457",
            "type": "leaf",
            "state": {
              "type": "bookmarks",
              "state": {},
              "icon": "lucide-bookmark",
              "title": "Bookmarks"
            }
          }
        ],
        "currentTab": 1
      }
    ],
    "direction": "horizontal",
    "width": 293.50312423706055
  },
  "right": {
    "id": "82bf382e913ed633",
    "type": "split",
    "children": [
      {
        "id": "05fbbbb6591f1691",
        "type": "tabs",
        "children": [
          {
            "id": "e5fd535eb84e009b",
            "type": "leaf",
            "state": {
              "type": "backlink",
              "state": {
                "file": "Topology/Algebraic Topology/p-Simplex.md",
                "collapseAll": false,
                "extraContext": false,
                "sortOrder": "alphabetical",
                "showSearch": false,
                "searchQuery": "",
                "backlinkCollapsed": false,
                "unlinkedCollapsed": true
              },
              "icon": "links-coming-in",
              "title": "Backlinks for p-Simplex"
            }
          },
          {
            "id": "35a3e8565c5b4d95",
            "type": "leaf",
            "state": {
              "type": "outgoing-link",
              "state": {
                "file": "Topology/Algebraic Topology/p-Simplex.md",
                "linksCollapsed": false,
                "unlinkedCollapsed": true
              },
              "icon": "links-going-out",
              "title": "Outgoing links from p-Simplex"
            }
          },
          {
            "id": "7837eea807a9d2c5",
            "type": "leaf",
            "state": {
              "type": "tag",
              "state": {
                "sortOrder": "frequency",
                "useHierarchy": true
              },
              "icon": "lucide-tags",
              "title": "Tags"
            }
          },
          {
            "id": "d2a2a97b96c60ea5",
            "type": "leaf",
            "state": {
              "type": "outline",
              "state": {
                "file": "Topology/Algebraic Topology/p-Simplex.md"
              },
              "icon": "lucide-list",
              "title": "Outline of p-Simplex"
            }
          }
        ]
      }
    ],
    "direction": "horizontal",
    "width": 300,
    "collapsed": true
  },
  "left-ribbon": {
    "hiddenItems": {
      "switcher:Open quick switcher": false,
      "graph:Open graph view": false,
      "canvas:Create new canvas": false,
      "daily-notes:Open today's daily note": false,
      "templates:Insert template": false,
      "command-palette:Open command palette": false,
      "3d-graph:3D Graph": false,
      "obsidian-to-anki-plugin:Obsidian_to_Anki - Scan Vault": false,
      "flashcards-obsidian:Generate flashcards": false
    }
  },
  "active": "b32d5576afc99c70",
  "lastOpenFiles": [
    "ML Theory/Laplace Approximation.md",
    "Markov Processes/Markov Chain.md",
    "Markov Processes/Stationary Distribution.md",
    "Linear Algebra/Cholesky Decomposition.md",
    "ML Theory/Variational Inference.md",
    "Probability Theory/Gaussian Distribution.md",
    "Courses/Probabilistic AI/Probabilistic AI Roadmap.md",
    "Analysis/Laplace Transform.md",
    "Probability Theory/Expected Value.md",
    "Measure Theory/Lebesgue Measure.md",
    "Measure Theory/Diffeomorphism.md",
    "Measure Theory/Summable Function.md",
    "Measure Theory/Product Measure.md",
    "Differential Geometry/Smooth Function.md",
    "Functional Analysis/Ergodic Measure.md",
    "Probability Theory/Independence.md",
    "Information Theory/Relative Entropy.md",
    "Analysis/Kernel.md",
    "Machine Learning/Linear Regression.md",
    "Machine Learning/Gaussian Process.md",
    "Information Theory/Entropy.md",
    "Functional Analysis/Fourier Transform.md",
    "Topology/Algebraic Topology/Relative Homology.md",
    "Courses/Advanced Algorithms/Exercise 02.md",
    "Courses/Advanced Algorithms/Exercise 09.md",
    "Courses/Advanced Algorithms/Graded Assignment 1.md",
    "Topology/Algebraic Topology",
    "Courses/Algebraic Topology I",
    "Untitled 1",
    "Set Theory",
    "Algorithms/Graph Algorithms",
    "Linear Algebra",
    "Commutative Algebra",
    "Logic",
    "Courses/Probabilistic AI",
    "Courses/Information Theory",
    "Courses/Algebra I/ARVST.jpeg"
  ]
}