{
  "main": {
    "id": "da9fa0f33c2a615f",
    "type": "split",
    "children": [
      {
        "id": "c45eeefa3389e702",
        "type": "tabs",
        "children": [
          {
            "id": "cd96f963b7fd8fe8",
            "type": "leaf",
            "state": {
              "type": "markdown",
              "state": {
                "file": "Functional Analysis/Unimodular Group.md",
                "mode": "source",
                "source": true
              }
            }
          },
          {
            "id": "54c8f18dfcc9b2a2",
            "type": "leaf",
            "state": {
              "type": "markdown",
              "state": {
                "file": "Courses/Lie Groups/Lie Groups Roadmap.md",
                "mode": "source",
                "source": true
              }
            }
          },
          {
            "id": "6a7b987e5ea1b218",
            "type": "leaf",
            "state": {
              "type": "markdown",
              "state": {
                "file": "Lie Group/Lattice.md",
                "mode": "source",
                "source": true
              }
            }
          }
        ],
        "currentTab": 2
      },
      {
        "id": "7e6b1dbc3952fb00",
        "type": "tabs",
        "children": [
          {
            "id": "6343fc6755c861ea",
            "type": "leaf",
            "state": {
              "type": "markdown",
              "state": {
                "file": "Lie Group/Topological Group.md",
                "mode": "preview",
                "source": false
              }
            }
          },
          {
            "id": "282d6b7b77d25cc4",
            "type": "leaf",
            "state": {
              "type": "markdown",
              "state": {
                "file": "Lie Group/Lattice.md",
                "mode": "source",
                "source": false
              }
            }
          },
          {
            "id": "8902c663e58dc621",
            "type": "leaf",
            "state": {
              "type": "markdown",
              "state": {
                "file": "Algebra/General Linear Group.md",
                "mode": "preview",
                "source": false
              }
            }
          },
          {
            "id": "3bc0b190a708e9b9",
            "type": "leaf",
            "state": {
              "type": "markdown",
              "state": {
                "file": "Algebra/General Linear Group.md",
                "mode": "preview",
                "source": false
              }
            }
          },
          {
            "id": "36984071045ffc68",
            "type": "leaf",
            "state": {
              "type": "markdown",
              "state": {
                "file": "Analysis/Inner Product Space.md",
                "mode": "source",
                "source": false
              }
            }
          }
        ],
        "currentTab": 2
      }
    ],
    "direction": "vertical"
  },
  "left": {
    "id": "74ebf3055b564f0b",
    "type": "split",
    "children": [
      {
        "id": "595ad8f59f37c1e1",
        "type": "tabs",
        "children": [
          {
            "id": "ee568ad677adda89",
            "type": "leaf",
            "state": {
              "type": "file-explorer",
              "state": {
                "sortOrder": "alphabetical"
              }
            }
          },
          {
            "id": "426a3c97ada45d5c",
            "type": "leaf",
            "state": {
              "type": "search",
              "state": {
                "query": "pre-compact",
                "matchingCase": false,
                "explainSearch": false,
                "collapseAll": false,
                "extraContext": false,
                "sortOrder": "alphabetical"
              }
            }
          },
          {
            "id": "60801509214fc457",
            "type": "leaf",
            "state": {
              "type": "bookmarks",
              "state": {}
            }
          }
        ]
      }
    ],
    "direction": "horizontal",
    "width": 268.50312423706055
  },
  "right": {
    "id": "82bf382e913ed633",
    "type": "split",
    "children": [
      {
        "id": "05fbbbb6591f1691",
        "type": "tabs",
        "children": [
          {
            "id": "e5fd535eb84e009b",
            "type": "leaf",
            "state": {
              "type": "backlink",
              "state": {
                "file": "Algebra/General Linear Group.md",
                "collapseAll": false,
                "extraContext": false,
                "sortOrder": "alphabetical",
                "showSearch": false,
                "searchQuery": "",
                "backlinkCollapsed": false,
                "unlinkedCollapsed": true
              }
            }
          },
          {
            "id": "35a3e8565c5b4d95",
            "type": "leaf",
            "state": {
              "type": "outgoing-link",
              "state": {
                "file": "Algebra/General Linear Group.md",
                "linksCollapsed": false,
                "unlinkedCollapsed": true
              }
            }
          },
          {
            "id": "7837eea807a9d2c5",
            "type": "leaf",
            "state": {
              "type": "tag",
              "state": {
                "sortOrder": "frequency",
                "useHierarchy": true
              }
            }
          },
          {
            "id": "d2a2a97b96c60ea5",
            "type": "leaf",
            "state": {
              "type": "outline",
              "state": {
                "file": "Algebra/General Linear Group.md"
              }
            }
          }
        ]
      }
    ],
    "direction": "horizontal",
    "width": 300,
    "collapsed": true
  },
  "left-ribbon": {
    "hiddenItems": {
      "switcher:Open quick switcher": false,
      "graph:Open graph view": false,
      "canvas:Create new canvas": false,
      "daily-notes:Open today's daily note": false,
      "templates:Insert template": false,
      "command-palette:Open command palette": false,
      "3d-graph:3D Graph": false
    }
  },
  "active": "8902c663e58dc621",
  "lastOpenFiles": [
    "Algebra/Special Linear Group.md",
    "Algebra/Orthogonal Group.md",
    "Algebra/Group Action.md",
    "Lie Group/Lattice.md",
    "Algebra/General Linear Group.md",
    "Functional Analysis/Haar Measure.md",
    "Analysis/Inner Product Space.md",
    "Algebra/Orbit and Stablizer.md",
    "Measure Theory/Lebesgue Measure.md",
    "Functional Analysis/Bounded Linear Map.md",
    "Functional Analysis/Hilbert-Schmidt Operator.md",
    "Lie Group/Topological Group.md",
    "Topology/Topology of Compact Convergence.md",
    "Topology/Compact-Open Topology.md",
    "Topology/Product Topology.md",
    "Courses/Lie Groups/Lie Groups Roadmap.md",
    "Algebra/Semi-direct Product.md",
    "Topology/Compact Space.md",
    "Topology/Connected Space.md",
    "Topology/Locally Compact Space.md",
    "Topology/Quotient Topology.md",
    "Functional Analysis/Uniformly Continuous Function.md",
    "Courses/Topology/Exercise Sheet 4.md",
    "Topology/Hausdorff Space.md",
    "Courses/Topology/Exercise Sheet 2.md",
    "Courses/Topology/Exercise Sheet 3.md",
    "Algebra/Untitled",
    "Courses/Graph Theory",
    "Graph Theory",
    "ML Theory",
    "Representation Theory",
    "Courses/Representation Theory",
    "Courses/Functional Analysis II/Untitled",
    "Courses/Analysis IV",
    "Lie Group",
    "Courses/Lie Groups",
    "Courses/Algebra I/ARVST.jpeg"
  ]
}